http_snapshot/__init__.py
http_snapshot/_fixtures.py
http_snapshot/_models.py
http_snapshot/_pytest_plugin.py
http_snapshot/_serializer.py
http_snapshot/_typing.py
http_snapshot/_utils.py
http_snapshot/py.typed
http_snapshot/_integrations/__init__.py
http_snapshot/_integrations/_httpx.py
http_snapshot/_integrations/_requests.py
http_snapshot-0.1.6.dist-info/licenses/LICENSE
http_snapshot-0.1.6.dist-info/METADATA
http_snapshot-0.1.6.dist-info/WHEEL
http_snapshot-0.1.6.dist-info/entry_points.txt
http_snapshot-0.1.6.dist-info/top_level.txt
http_snapshot-0.1.6.dist-info/RECORD
