Metadata-Version: 2.4
Name: http-snapshot
Version: 0.1.6
Summary: http-snapshot is a pytest plugin that snapshots requests made with popular Python HTTP clients.
Requires-Python: >=3.9
License-File: LICENSE
Requires-Dist: inline-snapshot>=0.27.2
Provides-Extra: httpx
Requires-Dist: httpx>=0.28.1; extra == "httpx"
Provides-Extra: requests
Requires-Dist: requests>=2.32.5; extra == "requests"
Dynamic: license-file
